Metadata-Version: 2.1
Name: onlinexml-editor
Version: 1.8.0
Summary: Utility to edit online.xml files, used in Sardana
Home-page: UNKNOWN
Author: Yury Matveyev
Author-email: yury.matveev@desy.de
License: GPLv3
Platform: UNKNOWN
Classifier: License :: OSI Approved :: GNU General Public License v3 (GPLv3)
Classifier: Programming Language :: Python
Classifier: Programming Language :: Python :: 3
Classifier: Programming Language :: Python :: 3.7
Classifier: Programming Language :: Python :: Implementation :: CPython
Classifier: Development Status :: 3 - Alpha
Requires-Python: >=3.7
